{
  "title": "Scorpios",
  "name": "Alexander Wolfe",
  "profession": "Wrestler",
  "image": "https://www.famousbirthdays.com/thumbnails/graham-aubrey-medium.jpg",
  "social_links": [
    "https://instagram.com/famousbirthdays",
    "https://www.tiktok.com/@famousbirthdays",
    "https://twitter.com/famousbirthdays",
    "https://www.youtube.com/@famousbirthdays"
  ],
  "birthday": "November 5, 1986",
  "birth_sign": "Scorpio",
  "birthplace": "Dresden, Germany",
  "age": "38 years old",
  "fans_also_viewed": [
    {
      "name": "Roman Reigns",
      "profession": "Wrestler",
      "link": "https://www.famousbirthdays.com/people/roman-reigns.html",
      "image": "https://www.famousbirthdays.com/thumbnails/reigns-roman-medium.jpg",
      "social_links": []
    },
    {
      "name": "Jey Uso",
      "profession": "Wrestler",
      "link": "https://www.famousbirthdays.com/people/jey-uso.html",
      "image": "https://www.famousbirthdays.com/thumbnails/uso-jey-medium.jpg",
      "social_links": []
    },
    {
      "name": "Cody Rhodes",
      "profession": "Wrestler",
      "link": "https://www.famousbirthdays.com/people/cody-rhodes.html",
      "image": "https://www.famousbirthdays.com/thumbnails/rhodes-cody-medium.jpg",
      "social_links": []
    },
    {
      "name": "Jimmy Uso",
      "profession": "Wrestler",
      "link": "https://www.famousbirthdays.com/people/jimmy-uso.html",
      "image": "https://www.famousbirthdays.com/thumbnails/uso-jimmy-medium.jpg",
      "social_links": []
    }
  ],
  "is_a_member_of": [
    {
      "title": "Scorpios",
      "image": "https://www.famousbirthdays.com/thumbnails/graham-aubrey-medium.jpg",
      "link": ""
    }
  ],
  "content": [
    {
      "header": "About",
      "content": "German professional wrestler who is known for competing in the SmackDown series in the WWE. He is also known for being a former NXT Tag Team Champion. He later worked under the name Axel Axeman Tischer in the German Wrestling Federation. He first began his training in wrestling at the age of thirteen in Dresden. He competed in the independent circuit throughout Germany and Europe before settling in at the WWE Performance Center in April of 2015. He made his television debut in NXT in July of 2015. He has won several accomplishments for his wrestling including the wXw Shotgun Championship and the wXw Unified World Wrestling Championship. His wrestling fame has led him to amass over 60,000 followers on Instagram. He was born and raised in Dresden, Saxony, East Germany. He was awarded the NXT Tag Team Championship withEric Youngin 2017."
    },
    {
      "header": "Popularity",
      "content": "Most Popular#52,163First Name Alexander#23Born in Dresden, Germany#1November 5 Athlete#9Athlete Born in Germany#35Last Name Wolfe#6"
    },
    {
      "header": "Alexander Wolfe Is A Member Of",
      "content": "38 Year OldsWrestlersFirst Name AlexanderScorpios"
    },
    {
      "header": "Alexander Wolfe Fans Also Viewed",
      "content": "Roman ReignsWrestlerJey UsoWrestlerCody RhodesWrestlerJimmy UsoWrestler"
    },
    {
      "header": "More November 5 Birthdays",
      "content": "Kris JennerReality StarLinnette RodriguezTikTok StarMoreMore ScorpiosSZAR&B Singer2xrakaiTwitch StarMore"
    },
    {
      "header": "More Scorpios",
      "content": "Kris JennerReality StarLinnette RodriguezTikTok StarMoreSZAR&B Singer2xrakaiTwitch StarMore"
    }
  ]
}